aipype/__init__.py
aipype/agent_run_result.py
aipype/base_task.py
aipype/conditional_task.py
aipype/llm_task.py
aipype/pipeline_agent.py
aipype/py.typed
aipype/search_task.py
aipype/task_context.py
aipype/task_dependencies.py
aipype/task_result.py
aipype/tool_executor.py
aipype/tool_registry.py
aipype/tools.py
aipype/transform_task.py
aipype/tasklib/__init__.py
aipype/tasklib/io/__init__.py
aipype/tasklib/io/file_save_task.py
aipype/tasklib/media/__init__.py
aipype/tasklib/media/audio_transcript_task.py
aipype/tasklib/media/extract_audio_from_video_task.py
aipype/tasklib/web/__init__.py
aipype/tasklib/web/batch_article_summarize_task.py
aipype/tasklib/web/url_fetch_task.py
aipype/utils/__init__.py
aipype/utils/base_searcher.py
aipype/utils/common.py
aipype/utils/display.py
aipype/utils/serper_searcher.py
aipype/utils/url_fetcher.py
aipype-0.1.0a5.dist-info/METADATA
aipype-0.1.0a5.dist-info/WHEEL
aipype-0.1.0a5.dist-info/RECORD
